jamldump/__init__.py
jamldump/jamldump.py
jamldump/jinja2.py
jamldump/py.typed
jamldump-1.1.0.dist-info/licenses/LICENSE
jamldump-1.1.0.dist-info/WHEEL
jamldump-1.1.0.dist-info/METADATA
jamldump-1.1.0.dist-info/RECORD
