Metadata-Version: 2.4
Name: jamldump
Version: 1.1.0
Summary: Opinionated YAML dump function for JSON serializable content.
Author: Matthias Dellweg
License-Expression: GPL-3.0-or-later
License-File: LICENSE
Classifier: Typing :: Typed
Requires-Dist: jinja2>=3.0.0,<4.0.0 ; extra == 'jinja2'
Requires-Python: >=3.10, <3.14
Provides-Extra: jinja2
